osreports
