Metadata-Version: 1.1
Name: osreports
Version: 0.1.1
Summary: Utilization Reporting for OpenStack Clouds
Home-page: https://github.com/alokjani/osreports
Author: Alok Jani
Author-email: Alok.Jani@ril.com
License: UNKNOWN
Platform: UNKNOWN
Classifier: Programming Language :: Python
Classifier: Development Status :: 4 - Beta
Classifier: Intended Audience :: System Administrators
Classifier: License :: OSI Approved :: Apache Software License
Classifier: Operating System :: OS Independent
Classifier: Environment :: OpenStack
